ImageRobot/Focus.py
ImageRobot/Image.py
ImageRobot/Keyboard.py
ImageRobot/Mouse.py
ImageRobot/RobotException.py
ImageRobot/__init__.py
ImageRobot/version.py
ImageRobot-1.3.3.dist-info/LICENSE
ImageRobot-1.3.3.dist-info/METADATA
ImageRobot-1.3.3.dist-info/WHEEL
ImageRobot-1.3.3.dist-info/top_level.txt
ImageRobot-1.3.3.dist-info/RECORD
