Metadata-Version: 2.1
Name: ImageRobot
Version: 1.3.3
Summary: A library used to do image recognition.
Home-page: https://github.com/Atyors/ImageRobot
Author: Rouyan Thi
Author-email: rouyanthi@gmail.com
License: UNKNOWN
Platform: UNKNOWN
Classifier: Programming Language :: Python
Classifier: Development Status :: 5 - Production/Stable
Classifier: Natural Language :: English
Classifier: Operating System :: OS Independent
Classifier: Programming Language :: Python :: 3.7
Classifier: License :: OSI Approved :: GNU General Public License v3 (GPLv3)
Requires-Dist: keyboard
Requires-Dist: numpy
Requires-Dist: opencv-python
Requires-Dist: pyautogui
Requires-Dist: pygetwindow
Requires-Dist: robotframework
